unidecode_pyo3-0.2.1.dist-info/METADATA
unidecode_pyo3-0.2.1.dist-info/WHEEL
unidecode_pyo3-0.2.1.dist-info/licenses/LICENSE
unidecode_rs/__init__.py
unidecode_rs/ffi.py
unidecode_rs/libunidecode_rs.so
unidecode_pyo3-0.2.1.dist-info/RECORD
