Metadata-Version: 2.4
Name: unidecode-pyo3
Version: 0.2.1
License-File: LICENSE
Summary: Rust-backed transliteration similar to Python Unidecode, with optional PyO3 bindings for Python
License: GPL-3.0-or-later
Requires-Python: >=3.8
